spalloc_server/__init__.py
spalloc_server/_version.py
spalloc_server/allocator.py
spalloc_server/area_to_rect.py
spalloc_server/async_bmp_controller.py
spalloc_server/configuration.py
spalloc_server/configuration_reloader.py
spalloc_server/controller.py
spalloc_server/coordinates.py
spalloc_server/job_queue.py
spalloc_server/links.py
spalloc_server/pack_tree.py
spalloc_server/polling_server_core.py
spalloc_server/server.py
spalloc_server-1!7.0.0.dist-info/LICENSE
spalloc_server-1!7.0.0.dist-info/LICENSE_POLICY.md
spalloc_server-1!7.0.0.dist-info/METADATA
spalloc_server-1!7.0.0.dist-info/WHEEL
spalloc_server-1!7.0.0.dist-info/entry_points.txt
spalloc_server-1!7.0.0.dist-info/top_level.txt
spalloc_server-1!7.0.0.dist-info/zip-safe
spalloc_server-1!7.0.0.dist-info/RECORD
