Metadata-Version: 2.1
Name: spalloc-server
Version: 1!7.0.0
Summary: A tool for partitioning and allocating large SpiNNaker machines into smaller ones on demand.
Home-page: https://github.com/SpiNNakerManchester/spalloc_server
Maintainer: SpiNNakerTeam
Maintainer-email: spinnakerusers@googlegroups.com
License: Apache-2.0
Keywords: spinnaker,allocation,packing management,supercomputer
Classifier: Development Status :: 5 - Production/Stable
Classifier: Intended Audience :: Developers
Classifier: Intended Audience :: Science/Research
Classifier: License :: OSI Approved :: Apache Software License
Classifier: Natural Language :: English
Classifier: Operating System :: POSIX :: Linux
Classifier: Operating System :: Microsoft :: Windows
Classifier: Operating System :: MacOS
Classifier: Programming Language :: Python :: 3
Classifier: Programming Language :: Python :: 3.7
Classifier: Programming Language :: Python :: 3.8
Classifier: Programming Language :: Python :: 3.9
Classifier: Programming Language :: Python :: 3.10
Classifier: Programming Language :: Python :: 3.11
Requires-Python: <4,>=3.7
License-File: LICENSE
License-File: LICENSE_POLICY.md
Requires-Dist: pytz
Requires-Dist: SpiNNMan (==1!7.0.0)
Provides-Extra: test
Requires-Dist: pytest-cov ; extra == 'test'
Requires-Dist: pylint ; extra == 'test'
Requires-Dist: testfixtures ; extra == 'test'
